{
  "$schema": "https://json-schema.org/draft/2020-12/schema",
  "$id": "project-definition.json",
  "title": "Project Definition",
  "description": "High-level project definition: problem context, goals, and core boundaries.",
  "type": "object",
  "properties": {
    "vision": {
      "allOf": [
        {
          "$ref": "common_expanded.json#/$defs/fieldWrapper"
        },
        {
          "properties": {
            "meta": {
              "$ref": "common_expanded.json#/$defs/fieldMeta"
            },
            "value": {
              "type": "string",
              "examples": [
                "Become the market leader in digital customer service"
              ]
            }
          },
          "required": [
            "meta",
            "value"
          ]
        }
      ]
    },
    "businessGoals": {
      "allOf": [
        {
          "$ref": "common_expanded.json#/$defs/fieldWrapper"
        },
        {
          "properties": {
            "meta": {
              "$ref": "common_expanded.json#/$defs/fieldMeta"
            },
            "value": {
              "type": "array",
              "items": {
                "type": "string"
              },
              "examples": [
                [
                  "Reduce support calls by 30%",
                  "Increase online conversion by 15%"
                ]
              ]
            }
          },
          "required": [
            "meta",
            "value"
          ]
        }
      ]
    },
    "problemStatement": {
      "allOf": [
        {
          "$ref": "common_expanded.json#/$defs/fieldWrapper"
        },
        {
          "properties": {
            "meta": {
              "$ref": "common_expanded.json#/$defs/fieldMeta"
            },
            "value": {
              "type": "string"
            }
          },
          "required": [
            "meta",
            "value"
          ]
        }
      ]
    },
    "outcomes": {
      "allOf": [
        {
          "$ref": "common_expanded.json#/$defs/fieldWrapper"
        },
        {
          "properties": {
            "meta": {
              "$ref": "common_expanded.json#/$defs/fieldMeta"
            },
            "value": {
              "type": "array",
              "items": {
                "$ref": "outcomes.json"
              }
            }
          },
          "required": [
            "meta",
            "value"
          ]
        }
      ]
    },
    "primaryStakeholders": {
      "allOf": [
        {
          "$ref": "common_expanded.json#/$defs/fieldWrapper"
        },
        {
          "properties": {
            "meta": {
              "$ref": "common_expanded.json#/$defs/fieldMeta"
            },
            "value": {
              "type": "array",
              "items": {
                "$ref": "stakeholders.json"
              }
            }
          },
          "required": [
            "meta",
            "value"
          ]
        }
      ]
    },
    "scopeSummary": {
      "allOf": [
        {
          "$ref": "common_expanded.json#/$defs/fieldWrapper"
        },
        {
          "properties": {
            "meta": {
              "$ref": "common_expanded.json#/$defs/fieldMeta"
            },
            "value": {
              "$ref": "scope.json"
            }
          },
          "required": [
            "meta",
            "value"
          ]
        }
      ]
    },
    "synthetic_field_0061": {
      "allOf": [
        {
          "$ref": "common_expanded.json#/$defs/fieldWrapper"
        },
        {
          "allOf": [
            {
              "$ref": "common_expanded.json#/$defs/entity_def_062"
            }
          ]
        }
      ]
    },
    "synthetic_field_0062": {
      "allOf": [
        {
          "$ref": "common_expanded.json#/$defs/fieldWrapper"
        },
        {
          "allOf": [
            {
              "$ref": "common_expanded.json#/$defs/entity_def_063"
            }
          ]
        }
      ]
    },
    "synthetic_field_0063": {
      "allOf": [
        {
          "$ref": "common_expanded.json#/$defs/fieldWrapper"
        },
        {
          "allOf": [
            {
              "$ref": "common_expanded.json#/$defs/entity_def_064"
            }
          ]
        }
      ]
    },
    "synthetic_field_0151": {
      "allOf": [
        {
          "$ref": "common_expanded.json#/$defs/fieldWrapper"
        },
        {
          "allOf": [
            {
              "$ref": "common_expanded.json#/$defs/entity_def_152"
            }
          ]
        }
      ]
    },
    "synthetic_field_0152": {
      "allOf": [
        {
          "$ref": "common_expanded.json#/$defs/fieldWrapper"
        },
        {
          "allOf": [
            {
              "$ref": "common_expanded.json#/$defs/entity_def_153"
            }
          ]
        }
      ]
    },
    "synthetic_field_0153": {
      "allOf": [
        {
          "$ref": "common_expanded.json#/$defs/fieldWrapper"
        },
        {
          "allOf": [
            {
              "$ref": "common_expanded.json#/$defs/entity_def_154"
            }
          ]
        }
      ]
    },
    "synthetic_field_0241": {
      "allOf": [
        {
          "$ref": "common_expanded.json#/$defs/fieldWrapper"
        },
        {
          "allOf": [
            {
              "$ref": "common_expanded.json#/$defs/entity_def_242"
            }
          ]
        }
      ]
    },
    "synthetic_field_0242": {
      "allOf": [
        {
          "$ref": "common_expanded.json#/$defs/fieldWrapper"
        },
        {
          "allOf": [
            {
              "$ref": "common_expanded.json#/$defs/entity_def_243"
            }
          ]
        }
      ]
    },
    "synthetic_field_0243": {
      "allOf": [
        {
          "$ref": "common_expanded.json#/$defs/fieldWrapper"
        },
        {
          "allOf": [
            {
              "$ref": "common_expanded.json#/$defs/entity_def_244"
            }
          ]
        }
      ]
    }
  },
  "required": [
    "vision",
    "businessGoals",
    "problemStatement"
  ],
  "additionalProperties": false,
  "$comment": "meta fields normalized to $ref to common_expanded.json#/$defs/fieldMeta"
}